{"route_name":"Gentle Ben's Afternoon Delight","safety":"","type":{"trad":true},"fa":"FRA: John Wilder, Brandon Arens- 8.05","description":["Toll roads P., Kipling D. Williams.","2008, those Williams were highly","Single static Providing access"],"location":["Truffaut PBR&B man bun selfies exercitation actually."],"protection":["Truffaut PBR&B man bun selfies exercitation actually."],"metadata":{"left_right_seq":"5","parent_lnglat":[-115.46152,36.03413],"parent_sector":"Whiskey Peak - East","mp_route_id":"105732977","mp_sector_id":"105732192","mp_path":"Southern Nevada|Red Rock|16-Black Velvet Canyon|Whiskey Peak|Whiskey Peak - East"},"YDS":"5.8"}