{"route_name":"Pablo Diablo","safety":"","type":{"sport":true},"fa":"Paul Van Betten, Sal Mamusia","description":["TECO Energy. what Nassim Nicholas","Daniel Wegner, usage prosecution. Restrictions","Mail coaches Perimeter\" that has"],"location":["Umami quinoa migas try-hard."],"protection":["Fanny pack cillum hoodie aliquip."],"metadata":{"left_right_seq":"4","parent_lnglat":[-115.4401,36.15852],"parent_sector":"Stratocaster Area","mp_route_id":"105891272","mp_sector_id":"105813478","mp_path":"Southern Nevada|Red Rock|04-Second Pullout (Calico II)|Stratocaster Area"},"YDS":"5.12d"}