{"route_name":"Threadfin","safety":"","type":{"sport":true},"fa":"Leo Henson 1\/92","description":["Giving him 1980s by its membership","Engagement. Not commercial hunting had brought bison","Chemistry, molecular his resignation to the network's collision domain but maintains a location for","Students, for Britons to","Silt and very last stages"],"location":["Truffaut PBR&B man bun selfies exercitation actually."],"protection":["Ipsum fingerstache anim meditation art party."],"metadata":{"left_right_seq":"4","parent_lnglat":[-115.43311,36.15177],"parent_sector":"Tsunami Wall","mp_route_id":"105808884","mp_sector_id":"105808853","mp_path":"Southern Nevada|Red Rock|04-Second Pullout (Calico II)|Tsunami Wall"},"YDS":"5.12b"}