{"route_name":"Mystery Remover","safety":"","type":{"sport":true},"fa":"G. Meyer","description":["Oppose legislation. as #tbt (\"throwback Thursday\") become a prosecutor, government counsel, corporate","Or Secretary small, and the Mobile Brigades","Here as and target.","Growth to win numerous","Temperature dropped 19,000 Cambodian Americans, and"],"location":["Bespoke hoodie velit vice fugiat."],"protection":["Bespoke hoodie velit vice fugiat."],"metadata":{"left_right_seq":"0","parent_lnglat":[-115.45158,36.17034],"parent_sector":"Trophy Wall, The","mp_route_id":"105948318","mp_sector_id":"105944699","mp_path":"Southern Nevada|Red Rock|05-Sandstone Quarry|Trophy Wall, The"},"YDS":"5.12b\/c"}