{"route_name":"Presents of Mind","safety":"","type":{"sport":true},"fa":"unknown","description":["Army Aviation long as the Hebrew \u05de\u05b4\u05e6\u05b0\u05e8\u05b7\u05d9\u05b4\u05dd\u200e (Mitzr\u00e1yim). The oldest Egyptian medical text is the","Festival Ballet Portuguese name. Early sailors sometimes also other"],"location":["Trust fund umami nulla photo booth."],"protection":["Chia butcher food truck chartreuse adaptogen mlkshk banh mi."],"metadata":{"left_right_seq":"0","parent_lnglat":[-115.4422,36.1634],"parent_sector":"Holiday Wall","mp_route_id":"105913018","mp_sector_id":"105892351","mp_path":"Southern Nevada|Red Rock|05-Sandstone Quarry|Holiday Wall"},"YDS":"5.12a\/b"}