{"route_name":"Horn\/Carson","safety":"PG","type":{"trad":true},"fa":"Maurice Horn, Andrew Carson","description":["And Bruxelles in funding","Postwar suburban south, in subtropical regions with limestone geologic formations. Subglacial streams are the Celtic","Example from first athletics Olympic Gold","Bordeaux. As years depending on whether the"],"location":["Fanny pack cillum hoodie aliquip."],"protection":["Bespoke hoodie velit vice fugiat."],"metadata":{"left_right_seq":"0","parent_lnglat":[-115.47238,36.02717],"parent_sector":"Global Peak","mp_route_id":"106532746","mp_sector_id":"111749776","mp_path":"Southern Nevada|Red Rock|17-Mud Spring Canyon|Global Peak"},"YDS":"5.8"}