{"route_name":"Vera's Roof","safety":"","type":{"boulder":true},"fa":"Vera Shulte-Pelkum","description":["The winds automobiles with absolutely no human presence in major urban agglomerations in the work","On-screen. Other on weather forecasting"],"location":["Umami quinoa migas try-hard."],"protection":["Bespoke hoodie velit vice fugiat."],"metadata":{"left_right_seq":"999999","parent_lnglat":[-115.41998,36.14221],"parent_sector":"Moderate Mecca","mp_route_id":"106627169","mp_sector_id":"115008710","mp_path":"Southern Nevada|Red Rock|* Red Rock Bouldering|Calico Basin Boulders|Moderate Mecca"},"YDS":"5.9"}