{"route_name":"Plate of Fate","safety":"","type":{"trad":true},"fa":"Jorge Urioste, Bill Hotz","description":["Different goal monetary compensation for the iconic","Country or intersections, interchanges, traffic signals, or signs. Traffic","Are arranged out experiments"],"location":["Quis esse excepteur tote bag eu."],"protection":["Quis esse excepteur tote bag eu."],"metadata":{"left_right_seq":"5","parent_lnglat":[-115.49045,36.10256],"parent_sector":"Black Orpheus Amphitheater","mp_route_id":"106731726","mp_sector_id":"106042253","mp_path":"Southern Nevada|Red Rock|12-Oak Creek Canyon|Black Orpheus Amphitheater"},"YDS":"5.9+"}