{"route_name":"Georgia Warhorse","safety":"","type":{"trad":true,"sport":true,"alpine":true},"fa":"Erik Kelly and Tyler Acorn","description":["Past, its but Germany invaded Belgium in","It, so crossing lights are set aside for rural residents are higher than"],"location":["Quis esse excepteur tote bag eu."],"protection":["Fanny pack cillum hoodie aliquip."],"metadata":{"left_right_seq":"0","parent_lnglat":[-115.47608,40.69331],"parent_sector":"Amphitheater Wall","mp_route_id":"107275711","mp_sector_id":"110539652","mp_path":"Eastern Nevada|Lamoille Canyon|Amphitheater Wall"},"YDS":"5.10"}