{"route_name":"Horizontal Departure","safety":"","type":{"trad":true},"fa":"Randy Marsh, Wendell Broussard, Pete Absolon, 1984","description":["A localized Empire, also known as physiological psychology.","Endemics. These for various"],"location":["Ipsum fingerstache anim meditation art party."],"protection":["Bespoke hoodie velit vice fugiat."],"metadata":{"left_right_seq":"1","parent_lnglat":[-115.41873,36.16649],"parent_sector":"Gateway Crag","mp_route_id":"107471856","mp_sector_id":"107471846","mp_path":"Southern Nevada|Red Rock|01-Calico Basin|Kraft Mountain Area|Gateway Crag"},"YDS":"5.10b"}