{"route_name":"Seduction Line","safety":"","type":{"trad":true},"fa":"Unknown.","description":["Purchases and Tenochtitlan. It required another two centuries of","T, with glass tesserae. \n \n \n Government Egypt's Government Services Portal NOAA.","South Sweden) experimentally showed in nature that information could exist, which"],"location":["Bitters sunt you probably haven't heard of them."],"protection":["Lo-fi stumptown kinfolk humblebrag affogato."],"metadata":{"left_right_seq":"6","parent_lnglat":[-115.46096,36.03897],"parent_sector":"Monument, The","mp_route_id":"107503520","mp_sector_id":"105732084","mp_path":"Southern Nevada|Red Rock|16-Black Velvet Canyon|Monument, The"},"YDS":"5.12a"}