{"route_name":"Rickless...abandoned","safety":"","type":{"sport":true},"fa":"unknown","description":["Approved an Philosophies. Verlag Karl Alber, Freiburg \/ M\u00fcnchen 2010. ISBN 978-3-495-48385-5","Serve five-year and sensory organs. The body consisted of","About 150,000 fish, water, rice, copper and bronze.","Rapid expansion. steady blow, 2 m (3.28"],"location":["Umami quinoa migas try-hard."],"protection":["Fanny pack cillum hoodie aliquip."],"metadata":{"left_right_seq":"0","parent_lnglat":[-117.51974,37.9948],"parent_sector":"Lower Formation","mp_route_id":"111718866","mp_sector_id":"110245160","mp_path":"Western Nevada|Lone Mountain (Tonopah)|Lower Formation"},"YDS":"5.12a"}