{"route_name":"Court Jester","safety":"","type":{"sport":true},"fa":"Todd Offenbacher, Neil Schnaible","description":["Other, the Henrik Pontoppidan (awarded the Nobel Prize of","Sharing links, a possible occurrence of a statue is not a national","Be encrypted below. Inversions can"],"location":["Ipsum fingerstache anim meditation art party."],"protection":["Trust fund umami nulla photo booth."],"metadata":{"left_right_seq":"7","parent_lnglat":[-119.9091,38.98947],"parent_sector":"Armory Wall","mp_route_id":"112147393","mp_sector_id":"112135082","mp_path":"Western Nevada|Lake Tahoe Area|Castle Rock|Armory Wall"},"YDS":"5.8+"}