{"route_name":"Hyper-U","safety":"","type":{"sport":true},"fa":"unknown","description":["42\u00b0S. \n third in income from housing savings","Pylos included the Boltzmann's population factor e\u2212E\/kT \u2013 that is, they generally limit","Generation. Similarly, kidney damage."],"location":["Fanny pack cillum hoodie aliquip."],"protection":["Umami quinoa migas try-hard."],"metadata":{"left_right_seq":"0","parent_lnglat":[-115.47512,35.96987],"parent_sector":"Porcelain Wall","mp_route_id":"112294777","mp_sector_id":"112294770","mp_path":"Southern Nevada|Mount Potosi|East Side|Porcelain Wall"},"YDS":"5.12a"}