{"route_name":"Muffin Man","safety":"","type":{"sport":true},"fa":"Jarrett Hunter","description":["\u00b0C at percentage is at making predictions, the more","Pathway is Alaska-related articles"],"location":["Farm-to-table cold-pressed pork belly iceland dolore vape green juice."],"protection":["Bespoke hoodie velit vice fugiat."],"metadata":{"left_right_seq":"10","parent_lnglat":[-115.51713,35.93431],"parent_sector":"Hustle Wall","mp_route_id":"112559402","mp_sector_id":"112559296","mp_path":"Southern Nevada|Mount Potosi|West Side|Sleepy Hollow|Lower Cliffs|Hustle Wall"},"YDS":"5.11c"}