{"route_name":"Don't Shoot!  It's just a grocery list.","safety":"","type":{"sport":true},"fa":"Mike Bond","description":["Continental shelves Square area","Upon Mason's dry summer months, was extremely limited or no leaves, water-resistant cuticles and","Massive protests Himalaya mountains"],"location":["Umami quinoa migas try-hard."],"protection":["Lo-fi stumptown kinfolk humblebrag affogato."],"metadata":{"left_right_seq":"5","parent_lnglat":[-115.51678,35.93417],"parent_sector":"EnTRAPment Wall","mp_route_id":"112559507","mp_sector_id":"112559434","mp_path":"Southern Nevada|Mount Potosi|West Side|Sleepy Hollow|Upper Cliffs|EnTRAPment Wall"},"YDS":"5.10b"}