{"route_name":"Unnamed 5.6","safety":"","type":{"trad":true,"tr":true},"fa":"unknown","description":["Low pressure to 2014\u20132016 estimates.","& Mary a pirate haven."],"location":["Lo-fi stumptown kinfolk humblebrag affogato."],"protection":["Trust fund umami nulla photo booth."],"metadata":{"left_right_seq":"0","parent_lnglat":[-115.42795,36.15204],"parent_sector":"Cowlick Crag","mp_route_id":"113972384","mp_sector_id":"105917681","mp_path":"Southern Nevada|Red Rock|01-Calico Basin|Cowlick Crag"},"YDS":"5.6"}