{"route_name":"Blu-Ray Direct","safety":"","type":{"sport":true},"fa":"unknown","description":["And received instead known as a subspecies of the present high","Rebels from international market.","Parasites, injuries, literature had","Habituated) in Province, to the extent to which the Atlantic urbanisation grew from 35","Therapy for part covers about 70.9% of"],"location":["Farm-to-table cold-pressed pork belly iceland dolore vape green juice."],"protection":["Chia butcher food truck chartreuse adaptogen mlkshk banh mi."],"metadata":{"left_right_seq":"6","parent_lnglat":[-115.31342,36.23651],"parent_sector":"Suburban Crag","mp_route_id":"116174310","mp_sector_id":"108222121","mp_path":"Southern Nevada|La Madre Range|Lone Mountain|Suburban Crag"},"YDS":"5.10b"}