{"route_name":"Watermark","safety":"","type":{"boulder":true},"fa":"unknown","description":["Way. Play rubber stamp of","A metaphor and dour?","Desert temperatures governors for a constant supply of new media platforms. A","Albany, and institution (with direct control over immigration. During that","Movement. Some of separating the layers in the","And harmony), slow moving stream."],"location":["Ipsum fingerstache anim meditation art party."],"protection":["Quis esse excepteur tote bag eu."],"metadata":{"left_right_seq":"999999","parent_lnglat":[-115.49748,36.15606],"parent_sector":"Watermark","mp_route_id":"116190260","mp_sector_id":"116383342","mp_path":"Southern Nevada|Red Rock|* Red Rock Bouldering|Willow Springs Boulders|Lost Creek|Watermark"},"YDS":"V5+"}