{"route_name":"The Big Splash","safety":"","type":{"sport":true},"fa":"Clayton L., Jan. 2019","description":["\"artistic\" and Earth herself in the 1830s; after the","As arid altocumulus or"],"location":["Bespoke hoodie velit vice fugiat."],"protection":["Truffaut PBR&B man bun selfies exercitation actually."],"metadata":{"left_right_seq":"3","parent_lnglat":[-114.28415,36.90248],"parent_sector":"2) Moon Sector","mp_route_id":"116369057","mp_sector_id":"116368815","mp_path":"Southern Nevada|Mormon Mountains|Wall of Misfortune|2) Moon Sector"},"YDS":"5.12c\/d"}