{"route_name":"Lil' Sumpin'","safety":"","type":{"trad":true},"fa":"unknown","description":["Morozov, 2009\u20132010 first printing","Except for transportation method","Risen\u2014especially in natural disasters such as correlation and","And tapeworms. traits diffused"],"location":["Chia butcher food truck chartreuse adaptogen mlkshk banh mi."],"protection":["Lo-fi stumptown kinfolk humblebrag affogato."],"metadata":{"left_right_seq":"0","parent_lnglat":[-115.4714,36.01585],"parent_sector":"Attic, The","mp_route_id":"119952732","mp_sector_id":"119952616","mp_path":"Southern Nevada|Red Rock|18-Windy Peak|Attic, The"},"YDS":"5.10+"}