{"route_name":"Jack O'Neill","safety":"","type":{"sport":true},"fa":"Jon O'Brien","description":["Doi:10.1016\/B978-0-08-097086-8.24095-6. ISBN on Triton","The status actions on social media to","Users Viber: Francisco Canaro, Julio de Caro and"],"location":["Chia butcher food truck chartreuse adaptogen mlkshk banh mi."],"protection":["Fanny pack cillum hoodie aliquip."],"metadata":{"left_right_seq":"8","parent_lnglat":[-115.52518,35.97231],"parent_sector":"Story Crag Main Wall","mp_route_id":"120271061","mp_sector_id":"120270714","mp_path":"Southern Nevada|Mount Potosi|West Side|Old Spanish Trail Crags (Story Crags)|Story Crag Main Wall"},"YDS":"5.12a"}